snaik/__init__.py
snaik/__main__.py
snaik/brain.py
snaik/food.py
snaik/game.py
snaik/leaderboard.py
snaik/snake.py
snaik/staterecorder.py
snaik/utils.py
snaik/window.py
snaik/resources/Roboto-Regular.ttf
snaik/resources/logo.svg
snaik/resources/sample_external.cpp
snaik-0.1.1.dist-info/METADATA
snaik-0.1.1.dist-info/WHEEL
snaik-0.1.1.dist-info/RECORD
